{
  "type": "minecraft:crafting_shapeless",
  "category": "misc",
  "ingredients": [
    {
      "tag": "c:gravels"
    },
    {
      "tag": "c:gravels"
    },
    {
      "tag": "c:gravels"
    },
    {
      "tag": "c:gravels"
    },
    {
      "tag": "c:sands"
    },
    {
      "tag": "c:sands"
    },
    {
      "tag": "c:sands"
    },
    {
      "tag": "c:sands"
    },
    {
      "item": "minecraft:cyan_dye"
    }
  ],
  "result": {
    "count": 8,
    "id": "minecraft:cyan_concrete_powder"
  }
}