{
  "__comment__": "This file was automatically created by mcresources",
  "type": "tfc:kaolin_disc_vein",
  "config": {
    "rarity": 10,
    "min_y": -8,
    "max_y": 1,
    "size": 18,
    "height": 6,
    "density": 1.0,
    "project": true,
    "random_name": "kaolin",
    "biomes": "#tfc:kaolin_clay_spawns_in",
    "indicator": {
      "depth": 35,
      "spread": 5,
      "rarity": 10,
      "underground_rarity": 1,
      "underground_count": 0,
      "blocks": [
        {
          "block": "tfc:plant/blood_lily"
        }
      ]
    },
    "blocks": []
  }
}