{
  "__comment__": "This file was automatically created by mcresources",
  "multipart": [
    {
      "when": {
        "north": true
      },
      "apply": {
        "model": "tfc:block/wood/gear_box_port/willow"
      }
    },
    {
      "when": {
        "north": false
      },
      "apply": {
        "model": "tfc:block/wood/gear_box_face/willow"
      }
    },
    {
      "when": {
        "south": true
      },
      "apply": {
        "model": "tfc:block/wood/gear_box_port/willow",
        "y": 180
      }
    },
    {
      "when": {
        "south": false
      },
      "apply": {
        "model": "tfc:block/wood/gear_box_face/willow",
        "y": 180
      }
    },
    {
      "when": {
        "east": true
      },
      "apply": {
        "model": "tfc:block/wood/gear_box_port/willow",
        "y": 90
      }
    },
    {
      "when": {
        "east": false
      },
      "apply": {
        "model": "tfc:block/wood/gear_box_face/willow",
        "y": 90
      }
    },
    {
      "when": {
        "west": true
      },
      "apply": {
        "model": "tfc:block/wood/gear_box_port/willow",
        "y": 270
      }
    },
    {
      "when": {
        "west": false
      },
      "apply": {
        "model": "tfc:block/wood/gear_box_face/willow",
        "y": 270
      }
    },
    {
      "when": {
        "down": true
      },
      "apply": {
        "model": "tfc:block/wood/gear_box_port/willow",
        "x": 90
      }
    },
    {
      "when": {
        "down": false
      },
      "apply": {
        "model": "tfc:block/wood/gear_box_face/willow",
        "x": 90
      }
    },
    {
      "when": {
        "up": true
      },
      "apply": {
        "model": "tfc:block/wood/gear_box_port/willow",
        "x": 270
      }
    },
    {
      "when": {
        "up": false
      },
      "apply": {
        "model": "tfc:block/wood/gear_box_face/willow",
        "x": 270
      }
    }
  ]
}