{
  "__comment__": "This file was automatically created by mcresources",
  "multipart": [
    {
      "apply": {
        "model": "tfc:block/rock/aqueduct/basalt/base"
      }
    },
    {
      "when": {
        "north": "false"
      },
      "apply": {
        "model": "tfc:block/rock/aqueduct/basalt/north"
      }
    },
    {
      "when": {
        "east": "false"
      },
      "apply": {
        "model": "tfc:block/rock/aqueduct/basalt/east"
      }
    },
    {
      "when": {
        "south": "false"
      },
      "apply": {
        "model": "tfc:block/rock/aqueduct/basalt/south"
      }
    },
    {
      "when": {
        "west": "false"
      },
      "apply": {
        "model": "tfc:block/rock/aqueduct/basalt/west"
      }
    }
  ]
}