{
  "__comment__": "This file was automatically created by mcresources",
  "type": "tfc:forest_entry",
  "config": {
    "climate": {
      "min_temperature": -3,
      "max_temperature": 11.6,
      "min_groundwater": 150,
      "max_groundwater": 340
    },
    "groundcover": [
      {
        "block": "tfc:wood/twig/chestnut"
      },
      {
        "block": "tfc:wood/fallen_leaves/chestnut"
      }
    ],
    "normal_tree": "tfc:tree/chestnut",
    "dead_tree": "tfc:tree/chestnut_dead",
    "fallen_log": "tfc:wood/log/chestnut",
    "fallen_leaves": "tfc:wood/fallen_leaves/chestnut",
    "bush_log": {
      "Name": "tfc:wood/wood/chestnut",
      "Properties": {
        "branch_direction": "down",
        "axis": "y"
      }
    },
    "bush_leaves": "tfc:wood/leaves/chestnut",
    "old_growth_tree": "tfc:tree/chestnut_large",
    "dead_chance": 1,
    "fallen_tree_chance": 8
  }
}