{
  "__comment__": "This file was automatically created by mcresources",
  "name": "野生作物",
  "category": "tfc:the_world",
  "icon": "tfc:wild_crop/wheat",
  "pages": [
    {
      "type": "patchouli:text",
      "text": "世界各地都能找到小團的$(thing)野生作物$()。$(br2)用手就可以收穫野生作物，當然$(thing)刀$()或其他鋒利的工具也行。它們會掉落$(thing)種子$()和一些$(thing)農產品$()。再次種植這些種子就可以種出人工栽培版本的作物。"
    },
    {
      "type": "patchouli:multiblock",
      "multiblock": {
        "pattern": [
          [
            "X"
          ],
          [
            "0"
          ]
        ],
        "mapping": {
          "X": "tfc:wild_crop/wheat"
        }
      },
      "name": "野生小麥",
      "text": "作為示例，這是$(l:mechanics/crops#wheat)小麥$()的野生版本。",
      "enable_visualize": false
    },
    {
      "type": "patchouli:text",
      "text": "每一種可以人工栽培的作物都有其野生版本。請參見$(l:mechanics/crops)農作物$()章節來查詢所有可以人工栽培的作物。野生作物和人工栽培的作物外觀相似，但在草叢中更不顯眼些。它們往往會生成於適合種植這種作物的氣候環境中，因此最好在適合那種作物的氣候環境中去尋找它。"
    },
    {
      "type": "tfc:multimultiblock",
      "text": "所有野生作物的變種",
      "multiblocks": [
        {
          "pattern": [
            [
              "X"
            ],
            [
              "0"
            ]
          ],
          "mapping": {
            "X": "tfc:wild_crop/barley"
          }
        },
        {
          "pattern": [
            [
              "X"
            ],
            [
              "0"
            ]
          ],
          "mapping": {
            "X": "tfc:wild_crop/oat"
          }
        },
        {
          "pattern": [
            [
              "X"
            ],
            [
              "0"
            ]
          ],
          "mapping": {
            "X": "tfc:wild_crop/rye"
          }
        },
        {
          "pattern": [
            [
              "X"
            ],
            [
              "Y"
            ],
            [
              "0"
            ]
          ],
          "mapping": {
            "X": "tfc:wild_crop/maize[part=top]",
            "Y": "tfc:wild_crop/maize[part=bottom]"
          }
        },
        {
          "pattern": [
            [
              "X"
            ],
            [
              "0"
            ]
          ],
          "mapping": {
            "X": "tfc:wild_crop/barley"
          }
        },
        {
          "pattern": [
            [
              "X"
            ],
            [
              "0"
            ]
          ],
          "mapping": {
            "X": "tfc:wild_crop/rice[fluid=water]"
          }
        },
        {
          "pattern": [
            [
              "X"
            ],
            [
              "0"
            ]
          ],
          "mapping": {
            "X": "tfc:wild_crop/beet"
          }
        },
        {
          "pattern": [
            [
              "X"
            ],
            [
              "0"
            ]
          ],
          "mapping": {
            "X": "tfc:wild_crop/cabbage"
          }
        },
        {
          "pattern": [
            [
              "X"
            ],
            [
              "0"
            ]
          ],
          "mapping": {
            "X": "tfc:wild_crop/carrot"
          }
        },
        {
          "pattern": [
            [
              "X"
            ],
            [
              "0"
            ]
          ],
          "mapping": {
            "X": "tfc:wild_crop/garlic"
          }
        },
        {
          "pattern": [
            [
              "X"
            ],
            [
              "Y"
            ],
            [
              "0"
            ]
          ],
          "mapping": {
            "X": "tfc:wild_crop/green_bean[part=top]",
            "Y": "tfc:wild_crop/green_bean[part=bottom]"
          }
        },
        {
          "pattern": [
            [
              "X"
            ],
            [
              "0"
            ]
          ],
          "mapping": {
            "X": "tfc:wild_crop/potato"
          }
        },
        {
          "pattern": [
            [
              "X"
            ],
            [
              "0"
            ]
          ],
          "mapping": {
            "X": "tfc:wild_crop/onion"
          }
        },
        {
          "pattern": [
            [
              "X"
            ],
            [
              "0"
            ]
          ],
          "mapping": {
            "X": "tfc:wild_crop/soybean"
          }
        },
        {
          "pattern": [
            [
              "X"
            ],
            [
              "0"
            ]
          ],
          "mapping": {
            "X": "tfc:wild_crop/squash"
          }
        },
        {
          "pattern": [
            [
              "X"
            ],
            [
              "Y"
            ],
            [
              "0"
            ]
          ],
          "mapping": {
            "X": "tfc:wild_crop/sugarcane[part=top]",
            "Y": "tfc:wild_crop/sugarcane[part=bottom]"
          }
        },
        {
          "pattern": [
            [
              "X"
            ],
            [
              "Y"
            ],
            [
              "0"
            ]
          ],
          "mapping": {
            "X": "tfc:wild_crop/tomato[part=top]",
            "Y": "tfc:wild_crop/tomato[part=bottom]"
          }
        },
        {
          "pattern": [
            [
              "X"
            ],
            [
              "Y"
            ],
            [
              "0"
            ]
          ],
          "mapping": {
            "X": "tfc:wild_crop/jute[part=top]",
            "Y": "tfc:wild_crop/jute[part=bottom]"
          }
        },
        {
          "pattern": [
            [
              "X"
            ],
            [
              "0"
            ]
          ],
          "mapping": {
            "X": "tfc:wild_crop/pumpkin"
          }
        },
        {
          "pattern": [
            [
              "X"
            ],
            [
              "0"
            ]
          ],
          "mapping": {
            "X": "tfc:wild_crop/melon"
          }
        }
      ]
    }
  ],
  "read_by_default": true,
  "sortnum": 6,
  "extra_recipe_mappings": {
    "tag:tfc:wild_crops": 0
  }
}