{
  "parent": "tfc:recipes/root",
  "rewards": {
    "recipes": [
      "tfc:stone/shale/shale_rock",
      "tfc:stone/shale/shale_cobble",
      "tfc:stone/shale/shale_cobble_stairs"
    ]
  },
  "criteria": {
    "has_stairs_recipe": {
      "trigger": "minecraft:recipe_unlocked",
      "conditions": {
        "recipe": "tfc:stone/shale/shale_cobble_stairs"
      }
    },
    "has_rock": {
      "trigger": "minecraft:inventory_changed",
      "conditions": {
        "items": [
          {
            "type": "forge:ore_dict",
            "ore": "rockShale"
          }
        ]
      }
    },
    "has_cobble": {
      "trigger": "minecraft:inventory_changed",
      "conditions": {
        "items": [
          {
            "type": "forge:ore_dict",
            "ore": "cobblestoneShale"
          }
        ]
      }
    },
    "has_stairs": {
      "trigger": "minecraft:inventory_changed",
      "conditions": {
        "items": [
          {
            "type": "forge:ore_dict",
            "ore": "stairCobblestoneShale"
          }
        ]
      }
    },
    "has_debug_wand": {
      "trigger": "minecraft:inventory_changed",
      "conditions": {
        "items": [
          {
            "item": "tfc:wand"
          }
        ]
      }
    }
  },
  "requirements": [
    [
      "has_debug_wand",
      "has_stairs_recipe",
      "has_rock",
      "has_cobble",
      "has_stairs"
    ]
  ]
}