{
  "__comment": "Generated by generateResources.py function: blockstate",
  "forge_marker": 1,
  "defaults": {
    "model": "pressure_plate",
    "textures": {
      "texture": "tfc:blocks/stonetypes/raw/schist",
      "particle": "tfc:blocks/stonetypes/raw/schist"
    }
  },
  "variants": {
    "normal": [
      {}
    ],
    "powered": {
      "false": {
        "model": "stone_pressure_plate_up"
      },
      "true": {
        "model": "stone_pressure_plate_down"
      }
    },
    "inventory": [
      {
        "model": "stone_pressure_plate_up"
      }
    ]
  }
}