{
  "multipart": [
    {
      "when": {
        "down": "true"
      },
      "apply": {
        "model": "tfc:block/plant/morning_glory"
      }
    },
    {
      "when": {
        "east": "true"
      },
      "apply": {
        "model": "tfc:block/plant/morning_glory",
        "x": 270,
        "y": 90
      }
    },
    {
      "when": {
        "north": "true"
      },
      "apply": {
        "model": "tfc:block/plant/morning_glory",
        "x": 270
      }
    },
    {
      "when": {
        "south": "true"
      },
      "apply": {
        "model": "tfc:block/plant/morning_glory",
        "x": 270,
        "y": 180
      }
    },
    {
      "when": {
        "up": "true"
      },
      "apply": {
        "model": "tfc:block/plant/morning_glory",
        "x": 180
      }
    },
    {
      "when": {
        "west": "true"
      },
      "apply": {
        "model": "tfc:block/plant/morning_glory",
        "x": 270,
        "y": 270
      }
    }
  ]
}