{
  "__comment__": "This file was automatically created by mcresources",
  "type": "tfc:canyon",
  "config": {
    "probability": 0.03,
    "y": {
      "type": "uniform",
      "min_inclusive": {
        "absolute": 10
      },
      "max_inclusive": {
        "absolute": 67
      }
    },
    "yScale": 3,
    "lava_level": {
      "above_bottom": 8
    },
    "aquifers_enabled": true,
    "vertical_rotation": {
      "type": "uniform",
      "min_inclusive": -0.125,
      "max_exclusive": 0.125
    },
    "shape": {
      "distance_factor": {
        "type": "uniform",
        "min_inclusive": 0.75,
        "max_exclusive": 1.0
      },
      "thickness": {
        "type": "trapezoid",
        "min": 0.0,
        "max": 6.0,
        "plateau": 2.0
      },
      "width_smoothness": 3,
      "horizontal_radius_factor": {
        "type": "uniform",
        "min_inclusive": 0.75,
        "max_exclusive": 1.0
      },
      "vertical_radius_default_factor": 1.0,
      "vertical_radius_center_factor": 0.0
    },
    "replaceable": "#minecraft:overworld_carver_replaceables"
  }
}