{
  "__comment__": "This file was automatically created by mcresources",
  "name": "Culturas selvagens",
  "category": "tfc:the_world",
  "icon": "tfc:textures/gui/book/icons/wild_crops.png",
  "pages": [
    {
      "type": "patchouli:text",
      "text": "$(thing)Culturas selvagens$() Pode ser encontrado espalhado pelo mundo, crescendo em pequenos manchas. Eles podem ser colhidos para alimentos e sementes, que podem ser cultivados na forma não-wild.$(br2)A colheita de culturas selvagens pode ser feita com os punhos ou com um $(thing)Faca$() ou outra ferramenta nítida. Quando quebrado, eles vão caiSementeshing)Seeds$() e alguns $(thing)Produtos$()."
    },
    {
      "type": "patchouli:multiblock",
      "multiblock": {
        "pattern": [
          [
            "X"
          ],
          [
            "0"
          ]
        ],
        "mapping": {
          "X": "tfc:wild_crop/wheat[mature=true]"
        }
      },
      "name": "Wild Wheat",
      "text": "Um exemplo de uma colheita selvagem, neste caso $(l:mechanics/crops#wheat)Trigo$().",
      "enable_visualize": false
    },
    {
      "type": "patchouli:text",
      "text": "There are many different types of wild crop - every crop that can be cultivated has a wild variant that can be found in the world somewhere. See the list of $(l:mechanics/crops)Crops$() for all different crops that can be grown. Wild crops will look similar to their cultivated counterparts, but are more hidden within the grass. Wild crops will spawn in climates near where the crop itself can be cultivated, so if looking for a specific crop, look in the climate where the crop can be cultivated. Wild crops are only mature from June to October. Otherwise, they appear dead until the next Summer."
    },
    {
      "type": "tfc:multimultiblock",
      "text": "Todas as diferentes variedades de colheita selvagem",
      "multiblocks": [
        {
          "pattern": [
            [
              "X"
            ],
            [
              "0"
            ]
          ],
          "mapping": {
            "X": "tfc:wild_crop/barley"
          }
        },
        {
          "pattern": [
            [
              "X"
            ],
            [
              "0"
            ]
          ],
          "mapping": {
            "X": "tfc:wild_crop/oat"
          }
        },
        {
          "pattern": [
            [
              "X"
            ],
            [
              "0"
            ]
          ],
          "mapping": {
            "X": "tfc:wild_crop/rye"
          }
        },
        {
          "pattern": [
            [
              "X"
            ],
            [
              "Y"
            ],
            [
              "0"
            ]
          ],
          "mapping": {
            "X": "tfc:wild_crop/maize[part=top]",
            "Y": "tfc:wild_crop/maize[part=bottom]"
          }
        },
        {
          "pattern": [
            [
              "X"
            ],
            [
              "0"
            ]
          ],
          "mapping": {
            "X": "tfc:wild_crop/barley"
          }
        },
        {
          "pattern": [
            [
              "X"
            ],
            [
              "0"
            ]
          ],
          "mapping": {
            "X": "tfc:wild_crop/rice[fluid=water]"
          }
        },
        {
          "pattern": [
            [
              "X"
            ],
            [
              "0"
            ]
          ],
          "mapping": {
            "X": "tfc:wild_crop/beet"
          }
        },
        {
          "pattern": [
            [
              "X"
            ],
            [
              "0"
            ]
          ],
          "mapping": {
            "X": "tfc:wild_crop/cabbage"
          }
        },
        {
          "pattern": [
            [
              "X"
            ],
            [
              "0"
            ]
          ],
          "mapping": {
            "X": "tfc:wild_crop/carrot"
          }
        },
        {
          "pattern": [
            [
              "X"
            ],
            [
              "0"
            ]
          ],
          "mapping": {
            "X": "tfc:wild_crop/garlic"
          }
        },
        {
          "pattern": [
            [
              "X"
            ],
            [
              "Y"
            ],
            [
              "0"
            ]
          ],
          "mapping": {
            "X": "tfc:wild_crop/green_bean[part=top]",
            "Y": "tfc:wild_crop/green_bean[part=bottom]"
          }
        },
        {
          "pattern": [
            [
              "X"
            ],
            [
              "0"
            ]
          ],
          "mapping": {
            "X": "tfc:wild_crop/potato"
          }
        },
        {
          "pattern": [
            [
              "X"
            ],
            [
              "0"
            ]
          ],
          "mapping": {
            "X": "tfc:wild_crop/onion"
          }
        },
        {
          "pattern": [
            [
              "X"
            ],
            [
              "0"
            ]
          ],
          "mapping": {
            "X": "tfc:wild_crop/soybean"
          }
        },
        {
          "pattern": [
            [
              "X"
            ],
            [
              "0"
            ]
          ],
          "mapping": {
            "X": "tfc:wild_crop/squash"
          }
        },
        {
          "pattern": [
            [
              "X"
            ],
            [
              "Y"
            ],
            [
              "0"
            ]
          ],
          "mapping": {
            "X": "tfc:wild_crop/sugarcane[part=top]",
            "Y": "tfc:wild_crop/sugarcane[part=bottom]"
          }
        },
        {
          "pattern": [
            [
              "X"
            ],
            [
              "Y"
            ],
            [
              "0"
            ]
          ],
          "mapping": {
            "X": "tfc:wild_crop/tomato[part=top]",
            "Y": "tfc:wild_crop/tomato[part=bottom]"
          }
        },
        {
          "pattern": [
            [
              "X"
            ],
            [
              "Y"
            ],
            [
              "0"
            ]
          ],
          "mapping": {
            "X": "tfc:wild_crop/jute[part=top]",
            "Y": "tfc:wild_crop/jute[part=bottom]"
          }
        },
        {
          "pattern": [
            [
              "X"
            ],
            [
              "0"
            ]
          ],
          "mapping": {
            "X": "tfc:wild_crop/pumpkin"
          }
        },
        {
          "pattern": [
            [
              "X"
            ],
            [
              "0"
            ]
          ],
          "mapping": {
            "X": "tfc:wild_crop/melon"
          }
        }
      ]
    }
  ],
  "read_by_default": true,
  "sortnum": 6,
  "extra_recipe_mappings": {
    "tag:tfc:wild_crops": 0
  }
}