{
  "parent":   "minecraft:block/block",
  "display":  {
	"ground": {
	  "translation": [    0,    3,    0 ],
	  "scale":       [ 0.25, 0.25, 0.25 ]
	},
	"gui": {
	  "rotation": [    30,   225,     0 ],
	  "scale":    [ 0.625, 0.625, 0.625 ]
		},
	"thirdperson_righthand": {
	  "rotation":    [    75,    45,     0 ],
	  "translation": [     0,   2.5,     0 ],
	  "scale":       [ 0.375, 0.375, 0.375 ]
	},
	"thirdperson_lefthand": {
	  "rotation":    [    75,    45,     0 ],
	  "translation": [     0,   2.5,     0 ],
	  "scale":       [ 0.375, 0.375, 0.375 ]
	},
	"firstperson_righthand": {
	  "rotation":    [   0,  45,   0 ],
	  "translation": [   0,   2,   0 ],
	  "scale":       [ 0.4, 0.4, 0.4 ]
	},
	"firstperson_lefthand": {
	  "rotation":    [   0,  45,   0 ],
	  "translation": [   0,   2,   0 ],
	  "scale":       [ 0.4, 0.4, 0.4 ]
	}
  },
  "elements": [
    {
	  "from":  [  3, 0,  3 ],
	  "to":    [ 13, 1, 13 ],
	  "faces": {
		"down": { "uv": [ 3, 3, 13, 13 ], "texture": "#bottom", "cullface": "down" },
		"up":   { "uv": [ 3, 3, 13, 13 ], "texture": "#bottom" }
	  }
	},
    {
	  "from":  [ 3,  0,  3 ],
	  "to":    [ 4, 10, 13 ],
	  "faces": {
		"west": { "uv": [ 3, 6, 13, 16 ], "texture": "#side" },
		"east": { "uv": [ 3, 6, 13, 16 ], "texture": "#side" }
	  }
	},
    {
	  "from":  [ 12,  0,  3 ],
	  "to":    [ 13, 10, 13 ],
	  "faces": {
		"west": { "uv": [ 3, 6, 13, 16 ], "texture": "#side" },
		"east": { "uv": [ 3, 6, 13, 16 ], "texture": "#side" }
	  }
	},
    {
	  "from":  [  3,  0, 3 ],
	  "to":    [ 13, 10, 4 ],
	  "faces": {
		"up":    { "uv": [ 13, 5,  3,  6 ], "texture": "#side" },
		"north": { "uv": [  3, 6, 13, 16 ], "texture": "#side" },
		"south": { "uv": [  3, 6, 13, 16 ], "texture": "#side" }
	  }
	},
    {
	  "from":  [  3,  0, 12 ],
	  "to":    [ 13, 10, 13 ],
	  "faces": {
		"up":    { "uv": [ 3, 5, 13,  6 ], "texture": "#side" },
		"north": { "uv": [ 3, 6, 13, 16 ], "texture": "#side" },
		"south": { "uv": [ 3, 6, 13, 16 ], "texture": "#side" }
	  }
	},
    {
	  "from":  [ 3, 10,  4 ],
	  "to":    [ 4, 10, 12 ],
	  "faces": {
		"up":   { "uv": [ 4, 4, 12, 5 ], "rotation": 90, "texture": "#side" }
	  }
	},
    {
	  "from":  [ 12, 10,  4 ],
	  "to":    [ 13, 10, 12 ],
	  "faces": {
		"up":   { "uv": [ 4, 5, 12, 6 ], "rotation": 270, "texture": "#side" }
	  }
	}
  ]
}